csemver.py
csemver-0.1.0.dist-info/LICENSE.md
csemver-0.1.0.dist-info/METADATA
csemver-0.1.0.dist-info/WHEEL
csemver-0.1.0.dist-info/top_level.txt
csemver-0.1.0.dist-info/RECORD
