Metadata-Version: 2.1
Name: csemver
Version: 0.1.0
Summary: Object orientied optimized variant of the semver package
Home-page: http://www.github.com/sebi2020/csemver
Author: Sebastian Tilders
Author-email: info@informatikonline.net
License: GPL3
Platform: any
Classifier: Programming Language :: Python :: 3
Classifier: Operating System :: OS Independent
Classifier: License :: OSI Approved :: GNU General Public License v3 (GPLv3)
Classifier: Topic :: Software Development :: Libraries
Classifier: Topic :: Software Development :: Version Control
Requires-Dist: semver
